pyzio/__init__.py
pyzio/i_pyzio.py
pyzio/pyzio.py
pyzio/pyzio_listener.py
pyzio/pyzio_logger.py
pyzio/pyzio_printer.py
pyzio/pyzio_settings.py
pyzio/config/__init__.py
pyzio/config/brainer_config.py
pyzio/config/mqtt_config.py
pyzio/config/mqtt_topics_config.py
pyzio/config/state_config.py
pyzio/domain/job.py
pyzio/enums/__init__.py
pyzio/enums/job_status.py
pyzio/enums/message_type.py
pyzio/enums/pair_status.py
pyzio/enums/print_file_type.py
pyzio/enums/printer_activity_state.py
pyzio/enums/sensor.py
pyzio/enums/sensor_type.py
pyzio/exceptions/__init__.py
pyzio/exceptions/error_messages.py
pyzio/exceptions/variable_exceptions.py
pyzio/handlers/__init__.py
pyzio/handlers/mqtt.py
pyzio/inject/container.py
pyzio/port/__init__.py
pyzio/port/phasio_control_port.py
pyzio/port/phasio_mqtt_port.py
pyzio/port/adapter/__init__.py
pyzio/port/adapter/brainer_client.py
pyzio/port/adapter/phasio_mqtt_adapter.py
pyzio/port/adapter/mqtt/__init__.py
pyzio/port/adapter/mqtt/message_factory.py
pyzio/port/adapter/mqtt/message_handler_factory.py
pyzio/port/adapter/mqtt/mqtt_operation_cache.py
pyzio/port/adapter/mqtt/phasio_mqtt_client.py
pyzio/repository/__init__.py
pyzio/repository/local_job_repository.py
pyzio/repository/printer_state_repository.py
pyzio/resource/__init__.py
pyzio/resource/i_platform_emitter.py
pyzio/resource/platform_emitter.py
pyzio/resource/platform_listener.py
pyzio/service/__init__.py
pyzio/service/i_job_service.py
pyzio/service/i_printer_service.py
pyzio/service/job_service.py
pyzio/service/printer_service.py
pyzio/service/update_service.py
Pyzio-1.3.5.dist-info/LICENSE
Pyzio-1.3.5.dist-info/METADATA
Pyzio-1.3.5.dist-info/WHEEL
Pyzio-1.3.5.dist-info/top_level.txt
Pyzio-1.3.5.dist-info/RECORD
