Metadata-Version: 2.1
Name: Pyzio
Version: 1.3.5
Summary: The Phasio Python client
Home-page: https://github.com/phas-io/Pyzio
Author: Phasio
Author-email: harry@phas.io
License: UNKNOWN
Project-URL: Bug Tracker, https://github.com/phas-io/Pyzio/issues
Platform: UNKNOWN
Classifier: Programming Language :: Python :: 3
Classifier: Operating System :: OS Independent
Requires-Python: >=3.6
License-File: LICENSE
